Metadata-Version: 2.4
Name: cdflow-cli
Version: 1.0.3
Summary: Caestudy DonationFlow - NationBuilder donation import CLI tool for external payment processors (CanadaHelps and PayPal)
Author-email: Mark Emila <mark.emila@caestudy.com>
License: BSL-1.1
Project-URL: Homepage, https://mkiiim.github.io/cdflow-cli/
Project-URL: Repository, https://github.com/mkiiim/cdflow-cli
Project-URL: Bug Tracker, https://github.com/mkiiim/cdflow-cli/issues
Keywords: nationbuilder,donations,import,canadahelps,paypal,cli,caestudy
Classifier: Development Status :: 5 - Production/Stable
Classifier: Intended Audience :: End Users/Desktop
Classifier: License :: Other/Proprietary License
Classifier: Operating System :: OS Independent
Classifier: Programming Language :: Python :: 3
Classifier: Programming Language :: Python :: 3.8
Classifier: Programming Language :: Python :: 3.9
Classifier: Programming Language :: Python :: 3.10
Classifier: Programming Language :: Python :: 3.11
Classifier: Topic :: Office/Business :: Financial
Classifier: Topic :: Utilities
Requires-Python: >=3.8
License-File: LICENSE
Requires-Dist: requests>=2.25.0
Requires-Dist: pyyaml>=6.0
Requires-Dist: chardet>=4.0.0
Requires-Dist: python-dateutil>=2.8.0
Requires-Dist: colorama>=0.4.4
Requires-Dist: pytz>=2021.1
Requires-Dist: langcodes[data]>=3.3.0
Requires-Dist: blessed>=1.17.0
Requires-Dist: pydantic>=1.8.0
Requires-Dist: uneff>=1.0.1
Requires-Dist: importlib-metadata>=1.0.0; python_version < "3.8"
Provides-Extra: dev
Requires-Dist: pytest>=6.0.0; extra == "dev"
Requires-Dist: pytest-cov>=2.10.0; extra == "dev"
Requires-Dist: black>=21.0.0; extra == "dev"
Requires-Dist: flake8>=3.8.0; extra == "dev"
Dynamic: license-file
